chinese/__init__.py
chinese/api.py
chinese/converter.py
chinese/dictionary.py
chinese/errors.py
chinese/tokenizer.py
chinese/data/cedict.pickle
chinese/data/dict.txt.big
chinese-0.2.1.dist-info/DESCRIPTION.rst
chinese-0.2.1.dist-info/METADATA
chinese-0.2.1.dist-info/RECORD
chinese-0.2.1.dist-info/WHEEL
chinese-0.2.1.dist-info/metadata.json
chinese-0.2.1.dist-info/top_level.txt
