Metadata-Version: 2.0
Name: chinese
Version: 0.2.1
Summary: Chinese text analyzer
Home-page: https://github.com/morinokami/chinese
Author: Shinya Fujino
Author-email: shf0811@gmail.com
License: MIT
Keywords: Chinese,text analysis
Platform: UNKNOWN
Classifier: Development Status :: 3 - Alpha
Classifier: Environment :: Other Environment
Classifier: Intended Audience :: Developers
Classifier: License :: OSI Approved :: MIT License
Classifier: Operating System :: MacOS :: MacOS X
Classifier: Operating System :: Microsoft :: Windows
Classifier: Operating System :: POSIX
Classifier: Programming Language :: Python :: 3
Classifier: Programming Language :: Python :: 3.6
Classifier: Programming Language :: Python :: 3 :: Only
Classifier: Topic :: Education
Classifier: Topic :: Text Processing :: Linguistic
Classifier: Topic :: Software Development :: Libraries :: Python Modules
Requires-Dist: jieba
Requires-Dist: pynlpir
